jiushu_logger_starlette/__init__.py
jiushu_logger_starlette/route_logging_middleware.py
jiushu_logger_starlette-1.0.2.dist-info/LICENSE
jiushu_logger_starlette-1.0.2.dist-info/WHEEL
jiushu_logger_starlette-1.0.2.dist-info/METADATA
jiushu_logger_starlette-1.0.2.dist-info/RECORD
