Metadata-Version: 2.1
Name: jiushu_logger_starlette
Version: 1.0.2
Summary: Jiushu logger for Starlette/FastAPI routes.
Author-email: Ai Tutu <zhixiao.yang0124@gmail.com>
Requires-Python: >=3.8
Classifier: License :: OSI Approved :: The Unlicense (Unlicense)
Classifier: Operating System :: OS Independent
Classifier: Programming Language :: Python :: 3
Classifier: Topic :: System :: Logging
Classifier: Typing :: Typed
Requires-Dist: jiushu-logger >=1.0.4
Requires-Dist: orjson >=3.8.0
Requires-Dist: python-ulid >=1.1.0
Requires-Dist: starlette[full] >=0.24.0
Project-URL: Bug Tracker, https://github.com/XiaoxiaFamily/jiushu-logger-starlette/issues
Project-URL: Homepage, https://github.com/XiaoxiaFamily/jiushu-logger-starlette
